textmatchertoolkit/__init__.py
textmatchertoolkit/toolkit.py
textmatchertoolkit-0.1.2.dist-info/METADATA
textmatchertoolkit-0.1.2.dist-info/WHEEL
textmatchertoolkit-0.1.2.dist-info/RECORD
